LICENSE
MANIFEST.in
README.md
requirements.txt
setup.cfg
setup.py
wpcmd/__init__.py
wpcmd/__main__.py
wpcmd/base.py
wpcmd/md.py
wpcmd/new.py
wpcmd/show.py
wpcmd/update.py
wpcmd/util.py
wpcmd/wpcmd.ini.tpl
wpcmd.egg-info/PKG-INFO
wpcmd.egg-info/SOURCES.txt
wpcmd.egg-info/dependency_links.txt
wpcmd.egg-info/entry_points.txt
wpcmd.egg-info/requires.txt
wpcmd.egg-info/top_level.txt
wpcmd/mde/__init__.py
wpcmd/mde/ditaa.py
wpcmd/mde/fenced_code_extra.py
wpcmd/mde/metadata.py
wpcmd/mde/plantuml.py