Metadata-Version: 1.1
Name: wpcmd
Version: 0.1.9
Summary: A command-line tool for WordPress.
Home-page: http://zengrong.net/wpcmd
Author: zrong
Author-email: zrongzrong@gmail.com
License: BSD
Keywords: utils development zrong wpcmd rookout wordpress xmlrpc
Platform: UNKNOWN
Classifier: Programming Language :: Python :: 3.4
Classifier: Development Status :: 4 - Beta
Classifier: Environment :: Console
Classifier: Environment :: Web Environment
Classifier: Operating System :: OS Independent
Classifier: Topic :: Internet :: WWW/HTTP :: Site Management
Classifier: Topic :: Utilities
Classifier: License :: OSI Approved :: BSD License
